psiutils/__init__.py
psiutils/_about_frame.py
psiutils/_logger.py
psiutils/_notify.py
psiutils/_version.py
psiutils/buttons.py
psiutils/constants.py
psiutils/drag_manager.py
psiutils/errors.py
psiutils/icecream_init.py
psiutils/icons/build.png
psiutils/icons/cancel.png
psiutils/icons/check.png
psiutils/icons/clear.png
psiutils/icons/code.png
psiutils/icons/compare.png
psiutils/icons/copy_clipboard.png
psiutils/icons/copy_docs.png
psiutils/icons/delete.png
psiutils/icons/diff.png
psiutils/icons/done.png
psiutils/icons/edit.png
psiutils/icons/gear.png
psiutils/icons/new.png
psiutils/icons/next.png
psiutils/icons/open.png
psiutils/icons/pause.png
psiutils/icons/preferences.png
psiutils/icons/previous.png
psiutils/icons/process.png
psiutils/icons/redo.png
psiutils/icons/refresh.png
psiutils/icons/rename.png
psiutils/icons/report.png
psiutils/icons/reset.png
psiutils/icons/revert.png
psiutils/icons/save.png
psiutils/icons/script.png
psiutils/icons/search.png
psiutils/icons/send.png
psiutils/icons/start.png
psiutils/icons/update.png
psiutils/icons/upgrade.png
psiutils/icons/windows.png
psiutils/images/icon-error.png
psiutils/images/icon-info.png
psiutils/images/icon-query.png
psiutils/known_paths.py
psiutils/menus.py
psiutils/messagebox.py
psiutils/text.py
psiutils/treeview.py
psiutils/utilities.py
psiutils/widgets.py
psiutils-0.2.14.dist-info/WHEEL
psiutils-0.2.14.dist-info/METADATA
psiutils-0.2.14.dist-info/RECORD
