Metadata-Version: 2.3
Name: psiutils
Version: 0.2.14
Summary: Various TKinter utilities.
Author: Jeff
Author-email: Jeff <<jeffwatkins2000@gmail.com>>
Requires-Dist: appdirs>=1.4.4
Requires-Dist: iniconfig>=2.1.0
Requires-Dist: markdown>=3.8.2
Requires-Dist: packaging>=25.0
Requires-Dist: pillow>=11.3.0
Requires-Dist: pluggy>=1.6.0
Requires-Dist: psi-toml>=0.0.12
Requires-Dist: psiconfig>=0.0.14
Requires-Dist: pycairo>=1.28.0
Requires-Dist: pygments>=2.19.2
Requires-Dist: pygobject>=3.54.2
Requires-Dist: structlog>=25.4.0
Requires-Dist: tkinterweb>=4.4.4
Requires-Dist: tkinterweb-tkhtml>=1.1.1
Requires-Dist: tomli>=2.2.1
Requires-Dist: tomli-w>=1.2.0
Requires-Python: >=3.10, <3.13
